README
setup-pypi.py
igor/__init__.py
igor/__main__.py
igor/consts.py
igor_inotify.egg-info/PKG-INFO
igor_inotify.egg-info/SOURCES.txt
igor_inotify.egg-info/dependency_links.txt
igor_inotify.egg-info/entry_points.txt
igor_inotify.egg-info/requires.txt
igor_inotify.egg-info/top_level.txt
igor_inotify.egg-info/zip-safe