Metadata-Version: 1.1
Name: igor-inotify
Version: 0.4
Summary: inotify based managment system
Home-page: http://code.pocketnix.org/hammerhead/file/tip
Author: Da_Blitz
Author-email: code@pocketnix.org
License: MIT BSD
Download-URL: http://code.pocketnix.org/igor/archive/tip.tar.bz2
Keywords: inotify linux managment
Platform: UNKNOWN
